kfpga/__init__.py
kfpga/common/__init__.py
kfpga/common/commands.py
kfpga/creator/__init__.py
kfpga/creator/__main__.py
kfpga/creator/commands.py
kfpga/creator/models.py
kfpga/creator/rtlgeneration/__init__.py
kfpga/creator/rtlgeneration/config.py
kfpga/creator/rtlgeneration/direction.py
kfpga/creator/rtlgeneration/module.py
kfpga/creator/rtlgeneration/side.py
kfpga/creator/rtlgeneration/writer.py
kfpga/creator/rtlgeneration/modules/__init__.py
kfpga/creator/rtlgeneration/modules/core.py
kfpga/creator/rtlgeneration/modules/dff.py
kfpga/creator/rtlgeneration/modules/logic_cluster.py
kfpga/creator/rtlgeneration/modules/logic_element.py
kfpga/creator/rtlgeneration/modules/logic_tile.py
kfpga/creator/rtlgeneration/modules/lut.py
kfpga/creator/rtlgeneration/modules/mux.py
kfpga/creator/rtlgeneration/modules/shift_register.py
kfpga/creator/rtlgeneration/modules/switch_box.py
kfpga-0.0.1.dist-info/LICENSE.EN.txt
kfpga-0.0.1.dist-info/LICENSE.FR.txt
kfpga-0.0.1.dist-info/LICENSE.tpl.py
kfpga-0.0.1.dist-info/METADATA
kfpga-0.0.1.dist-info/WHEEL
kfpga-0.0.1.dist-info/entry_points.txt
kfpga-0.0.1.dist-info/top_level.txt
kfpga-0.0.1.dist-info/RECORD
