Metadata-Version: 2.1
Name: kfpga
Version: 0.0.1
Summary: An open source FPGA
Home-page: https://git.slaanesh.org/killruana/kfpga
Author: Jonathan Tremesaygues
Author-email: jonathan.tremesaygues@slaanesh.org
License: CECILL-B
Keywords: kfpga fpga
Platform: UNKNOWN
Classifier: Programming Language :: Python :: 3
Classifier: License :: CeCILL-B Free Software License Agreement (CECILL-B)
Classifier: Operating System :: OS Independent
Requires-Python: ~=3.7
